django_sorting_field/__init__.py
django_sorting_field/fields.py
django_sorting_field/utils.py
django_sorting_field/widgets.py
django_sorting_field/static/sorting/css/sorting_widget.css
django_sorting_field/static/sorting/js/html.sortable.min.js
django_sorting_field/static/sorting/js/sorting_widget.js
django_sorting_field/templates/sorting/widgets/sorting_widget.html
django_sorting_field-1.0.2.dist-info/DESCRIPTION.rst
django_sorting_field-1.0.2.dist-info/LICENSE.txt
django_sorting_field-1.0.2.dist-info/METADATA
django_sorting_field-1.0.2.dist-info/RECORD
django_sorting_field-1.0.2.dist-info/WHEEL
django_sorting_field-1.0.2.dist-info/metadata.json
django_sorting_field-1.0.2.dist-info/top_level.txt
