Metadata-Version: 2.0
Name: django-sorting-field
Version: 1.0.2
Summary: Django Sorting Field
Home-page: UNKNOWN
Author: UNKNOWN
Author-email: UNKNOWN
License: MIT
Keywords: sorting,field,django
Platform: UNKNOWN
Requires-Dist: django
Requires-Dist: six
